cachedprop/__init__.py
cachedprop/src.py
cachedprop-0.1.0.dist-info/WHEEL
cachedprop-0.1.0.dist-info/METADATA
cachedprop-0.1.0.dist-info/RECORD
