Metadata-Version: 2.1
Name: cachedprop
Version: 0.1.0
Summary: cached property method decorator
Home-page: UNKNOWN
License: UNKNOWN
Author: Joao Valverde
Author-email: acci.valverde@gmail.com
Requires-Python: >=3.6,<4.0
Classifier: Programming Language :: Python :: 3
Classifier: Programming Language :: Python :: 3.6
Classifier: Programming Language :: Python :: 3.7
Requires-Dist: flake8 (>=3.6,<4.0)
